file_ext_sorter/__init__.py
file_ext_sorter/__main__.py
file_ext_sorter/cli/__init__.py
file_ext_sorter/cli/cli.py
file_ext_sorter/cli/cli_output.py
file_ext_sorter/cli/parser.py
file_ext_sorter/core/__init__.py
file_ext_sorter/core/file_entry.py
file_ext_sorter/core/files.py
file_ext_sorter/core/myaiopath.py
file_ext_sorter/core/sorter.py
file_ext_sorter/main.py
file_ext_sorter/utils/__init__.py
file_ext_sorter/utils/exit_codes.py
file_ext_sorter/utils/hash_calculator.py
file_ext_sorter/utils/logger_config.py
file_ext_sorter/utils/project_meta.py
file_ext_sorter-0.1.0.dist-info/LICENSE
file_ext_sorter-0.1.0.dist-info/METADATA
file_ext_sorter-0.1.0.dist-info/WHEEL
file_ext_sorter-0.1.0.dist-info/entry_points.txt
file_ext_sorter-0.1.0.dist-info/RECORD
