Metadata-Version: 2.3
Name: file-ext-sorter
Version: 0.1.0
Summary: A Python CLI tool to sort files by their extension
License: MIT
Author: Oleksandr Romashko
Author-email: alex.rmshk@gmail.com
Requires-Python: >=3.8, <3.15
Classifier: Programming Language :: Python :: 3
Classifier: Programming Language :: Python :: 3.8
Classifier: Programming Language :: Python :: 3.9
Classifier: Programming Language :: Python :: 3.10
Classifier: Programming Language :: Python :: 3.11
Classifier: Programming Language :: Python :: 3.12
Classifier: Programming Language :: Python :: 3.13
Classifier: Programming Language :: Python :: 3.14
Classifier: Operating System :: OS Independent
Classifier: Environment :: Console
Provides-Extra: dev
Requires-Dist: aiofiles (>=24.1.0,<25.0.0)
Requires-Dist: aioshutil (>=1.5,<2.0)
Requires-Dist: colorama (>=0.4.6,<0.5.0)
Requires-Dist: tomli (>=2.2.1) ; python_version < "3.11"
Requires-Dist: types-colorama (>=0.4.15.20240311) ; extra == "dev"
Project-URL: Homepage, https://github.com/oleksandr-romashko/goit-pythonweb-hw-04
Project-URL: Issues, https://github.com/oleksandr-romashko/goit-pythonweb-hw-04/issues
